lexical_diversity/__init__.py
lexical_diversity/e_lemma_lower_clean.txt
lexical_diversity/lex_div.py
lexical_diversity-0.1.1.dist-info/METADATA
lexical_diversity-0.1.1.dist-info/WHEEL
lexical_diversity-0.1.1.dist-info/top_level.txt
lexical_diversity-0.1.1.dist-info/RECORD
