Metadata-Version: 2.1
Name: lexical_diversity
Version: 0.1.1
Summary: A simple program for calcuating lexical diversity
Home-page: https://github.com/kristopherkyle/lexical_diversity
Author: Kristopher Kyle
Author-email: kristopherkyle1@gmail.com
License: UNKNOWN
Platform: UNKNOWN
Classifier: Programming Language :: Python :: 3
Classifier: License :: OSI Approved :: MIT License
Classifier: Operating System :: OS Independent
